explain_this_repo/__init__.py
explain_this_repo/__main__.py
explain_this_repo/cli.py
explain_this_repo/generate.py
explain_this_repo/github.py
explain_this_repo/prompt.py
explain_this_repo/repo_reader.py
explain_this_repo/stack_detector.py
explain_this_repo/stack_printer.py
explain_this_repo/writer.py
explainthisrepo-0.2.4.dist-info/licenses/LICENSE
explainthisrepo-0.2.4.dist-info/METADATA
explainthisrepo-0.2.4.dist-info/WHEEL
explainthisrepo-0.2.4.dist-info/entry_points.txt
explainthisrepo-0.2.4.dist-info/top_level.txt
explainthisrepo-0.2.4.dist-info/RECORD
