Metadata-Version: 2.4
Name: explainthisrepo
Version: 0.2.4
Summary: ExplainThisRepo is a CLI developer tool to quickly explain GitHub repository in plain English
Author-email: Caleb Wodi <calebwodi33@gmail.com>
License: MIT
Classifier: Programming Language :: Python :: 3
Classifier: Programming Language :: Python :: 3.9
Classifier: Programming Language :: Python :: 3.10
Classifier: Programming Language :: Python :: 3.11
Classifier: Programming Language :: Python :: 3.12
Classifier: License :: OSI Approved :: MIT License
Classifier: Operating System :: OS Independent
Requires-Python: >=3.9
License-File: LICENSE
Requires-Dist: requests
Provides-Extra: gemini
Requires-Dist: google-genai>=1.0.0; extra == "gemini"
Dynamic: license-file
